muarch-0.2.2.dist-info/WHEEL
muarch-0.2.2.dist-info/METADATA
muarch-0.2.2.dist-info/top_level.txt
muarch-0.2.2.dist-info/RECORD
muarch/exceptions.py
muarch/summary.py
muarch/_version.py
muarch/typings.py
muarch/__init__.py
muarch/uarch.py
muarch/muarch.py
muarch/datasets/__init__.py
muarch/datasets/load_datasets.py
muarch/datasets/data/etf.csv
muarch/distributions/normal.py
muarch/distributions/_base.py
muarch/distributions/__init__.py
muarch/distributions/student.py
muarch/distributions/ged.py
muarch/distributions/skew_student.py
muarch/mean/_mean_simulations.pyx
muarch/mean/_mean_simulations.cpython-37m-x86_64-linux-gnu.so
muarch/mean/_mean_simulations.c
muarch/mean/__init__.py
muarch/mean/models.py
muarch/mean/simulators.py
muarch/funcs/time_unit.py
muarch/funcs/moments.py
muarch/funcs/__init__.py
muarch/calibrate/_calibrate_sd.py
muarch/calibrate/_calibrate_both.py
muarch/calibrate/calibrate.py
muarch/calibrate/__init__.py
muarch/calibrate/truncate.py
muarch/calibrate/_calibrate_mean.py
muarch/calibrate/_calibrate_utils.py
muarch/volatility/_vol_simulations.pyx
muarch/volatility/_vol_simulations.c
muarch/volatility/__init__.py
muarch/volatility/models.py
muarch/volatility/_vol_simulations.cpython-37m-x86_64-linux-gnu.so
muarch/volatility/simulators.py
